resinkit/__init__.py
resinkit/resinkit.py
resinkit/core/resinkit_api_client.py
resinkit/core/task.py
resinkit/ui/__init__.py
resinkit/ui/sql_task_ui.py
resinkit/ui/tasks_management_ui.py
resinkit/ui/variables_ui.py
resinkit_sdk_python-0.1.1.dist-info/METADATA
resinkit_sdk_python-0.1.1.dist-info/WHEEL
resinkit_sdk_python-0.1.1.dist-info/licenses/LICENSE
resinkit_sdk_python-0.1.1.dist-info/RECORD
