Metadata-Version: 2.4
Name: resinkit-sdk-python
Version: 0.1.1
Summary: A Python SDK for ResinKit
Author-email: "resink.ai" <contact@resink.ai>
License-File: LICENSE
Requires-Python: >=3.10
Requires-Dist: flink-job-manager-api>=1.0.2
Requires-Dist: flink-sql-gateway-api==1.19.0
Requires-Dist: ipywidgets>=8.1.0
Requires-Dist: jupyter-bokeh>=4.0.5
Requires-Dist: pandas<3,>=2.0.0
Requires-Dist: panel>=1.7.0
